[
  {
    "name": "01 Etenraku 2",
    "slug": "01-etenraku-2",
    "album": "Japon. Gagaku",
    "artist": "Société Ono Gagaku Kaï",
    "year": "1979",
    "country": "Japon"
  },
  {
    "name": "04 Improvisation Dans Le Mode Triste-Solo De Dan Tranh-1",
    "slug": "04-improvisation-dans-le-mode-triste-solo-de-dan-tranh-1",
    "album": "Vietnam Improvisations-New Traditional",
    "artist": "Khe/Hai/Ngoc",
    "year": "1973",
    "country": "Vietnam"
  },
  {
    "name": "04. Goin' To See My Baby",
    "slug": "04-goin-to-see-my-baby",
    "album": "Bride of The Holy Ghost",
    "artist": "The Fatback Band",
    "year": "1972",
    "country": "Nueva York"
  },
  {
    "name": "07 eil malei rachmim",
    "slug": "07-eil-malei-rachmim",
    "album": "String Of Pearls: Jewels Of The 78rpm Era 1918-1951 (2009, Mississippi/Canary)",
    "artist": "Shalom Katz",
    "year": "1947",
    "country": "Hungria"
  },
  {
    "name": "08 - Le Plat Pays",
    "slug": "08-le-plat-pays",
    "album": "Olympia 64 (Live) (Cd 9)",
    "artist": "Jacques Brel",
    "year": "1964",
    "country": "Paris"
  },
  {
    "name": "1-05 Candra Kanta",
    "slug": "1-05-candra-kanta",
    "album": "Bali: Hommage à Wayan Lotring. Disc One",
    "artist": "Wayan Lotring",
    "year": "1972",
    "country": "Bali"
  },
  {
    "name": "10-Black_woodpecker-Zwarte+Specht-Dryocopus_martius 2",
    "slug": "10-black-woodpecker-zwarte-specht-dryocopus-martius-2",
    "album": "Listen the birds vol 4",
    "artist": "Black Woodpecker",
    "year": "1970",
    "country": "Holanda"
  },
  {
    "name": "13 Song Words Spoken By Gamargadada",
    "slug": "13-song-words-spoken-by-gamargadada",
    "album": "Songs From The Northern Territory: 2",
    "artist": "Gamargadada",
    "year": "1963",
    "country": "Numbulwar"
  },
  {
    "name": "2-23 Wayfaring Pilgrim",
    "slug": "2-23-wayfaring-pilgrim",
    "album": "THE OLD, WEIRD AMERICA_seleccion",
    "artist": "Clarence 'Tom' Ashley ",
    "year": "1961",
    "country": "Tennessee"
  },
  {
    "name": "31 Chant sur la mer",
    "slug": "31-chant-sur-la-mer",
    "album": "Kamtchatka: Tambours de danse de l'extrême-orient Sibérien",
    "artist": "Petr Evljkhovic Kotginin",
    "year": "1994",
    "country": "Kamtchatka"
  },
  {
    "name": "5-12 Songs From Maningrida and Cape St",
    "slug": "5-12-songs-from-maningrida-and-cape-st",
    "album": "Songs From The Northern Territory: 5",
    "artist": "Various",
    "year": "1962",
    "country": "Milingimbi"
  },
  {
    "name": "9-Java-Gamelan_Slendro-SekarGadung",
    "slug": "9-java-gamelan-slendro-sekargadung",
    "album": "Musik der Orient - 1930 compilatie Dr Erich von  Hornbostel",
    "artist": "Various",
    "year": "1930",
    "country": "Indonesia"
  },
  {
    "name": "B2-Palabra_Sortija",
    "slug": "b2-palabra-sortija",
    "album": "Bandurras de Canchis",
    "artist": "Conjunto Santa Barbara de Sicuani",
    "year": "19¿¿",
    "country": "Sicuani"
  },
  {
    "name": "CD1 22 Argentina [Selknam] Shaman's song",
    "slug": "cd1-22-argentina-selknam-shaman-s-song",
    "album": "Voices of the World - An Anthology of Vocal Expression - Techniques",
    "artist": "Lola Kiepja",
    "year": "1996",
    "country": "Isla Grande de Tierra del Fuego"
  },
  {
    "name": "Leb Tatefaletch - 17",
    "slug": "leb-tatefaletch-17",
    "album": "Ethiopiques 9",
    "artist": "Alèmayèhu Eshète",
    "year": "1969",
    "country": "Etiopia"
  },
  {
    "name": "Morning Prayer In Okbap",
    "slug": "morning-prayer-in-okbap",
    "album": "Irian Jaya: Disc Six",
    "artist": "Various",
    "year": "1973",
    "country": "Papua-Nueva Guinea"
  },
  {
    "name": "The Story of the Music Box 14 The Gypsy Baron (Gallop)",
    "slug": "the-story-of-the-music-box-14-the-gypsy-baron-gallop",
    "album": "The Story of the Music Box",
    "artist": "Concert",
    "year": "1885",
    "country": "Austria"
  },
  {
    "name": "b12-XII-Capricorn",
    "slug": "b12-xii-capricorn",
    "album": "Music Im Bauch-Tierkreis",
    "artist": "Karlheinz Stockhausen",
    "year": "1975",
    "country": "Alemania"
  },
  {
    "name": "northern lights(46)",
    "slug": "northern-lights-46",
    "album": "Music of the Northern lights",
    "artist": "Ensemble ",
    "year": "1964",
    "country": "Khabarovsk Krai"
  },
  {
    "name": "u9400",
    "slug": "u9400",
    "album": "The Nagas Hill Peoples of Northeast India",
    "artist": "Various",
    "year": "19¿¿",
    "country": "India-Nagaland"
  }
]